sremail/__init__.py
sremail/address.py
sremail/email_date_field.py
sremail/message.py
sremail/smtp.py
sremail-1.0.1.dist-info/LICENSE
sremail-1.0.1.dist-info/METADATA
sremail-1.0.1.dist-info/WHEEL
sremail-1.0.1.dist-info/top_level.txt
sremail-1.0.1.dist-info/RECORD
