Metadata-Version: 2.1
Name: sremail
Version: 1.0.1
Summary: Python package to make it easier to handle email.
Home-page: https://github.com/glasswall-sre/sremail
Author: Sam Gibson
Author-email: sgibson@glasswallsolutions.com
License: UNKNOWN
Platform: UNKNOWN
Classifier: Development Status :: 5 - Production/Stable
Classifier: Intended Audience :: Developers
Classifier: License :: OSI Approved :: MIT License
Classifier: Operating System :: OS Independent
Classifier: Programming Language :: Python :: 3.6
Classifier: Programming Language :: Python :: 3.7
Classifier: Programming Language :: Python :: 3.8
Classifier: Topic :: Communications :: Email
Classifier: Topic :: Software Development :: Libraries
Requires-Python: >=3.6
Requires-Dist: marshmallow
Requires-Dist: aiosmtplib
